pathlibext/__init__.py
pathlibext/find.py
pathlibext/json.py
pathlibext/match.py
pathlibext/rmtree.py
pathlibext/shell.py
pathlibext/stat.py
pathlibext/tmpdir.py
pathlibext/tmpfile.py
pathlibext/workdir.py
pathlibext-0.0.4.dist-info/LICENSE
pathlibext-0.0.4.dist-info/METADATA
pathlibext-0.0.4.dist-info/WHEEL
pathlibext-0.0.4.dist-info/top_level.txt
pathlibext-0.0.4.dist-info/RECORD
