Metadata-Version: 2.1
Name: pathlibext
Version: 0.0.4
Summary: Extends the functionalities of Pythion Pathlib
Home-page: https://github.com/gpcimino/pathlibext
Author: Giampaolo Cimino
Project-URL: Bug Tracker, https://github.com/gpcimino/pathlibext/issues
Classifier: Programming Language :: Python :: 3
Classifier: License :: OSI Approved :: MIT License
Classifier: Operating System :: OS Independent
Requires-Python: >=3.6
License-File: LICENSE
